{
  "version": "2.0",
  "lastUpdated": "2026-03-12T06:02:52.650Z",
  "activeFeatures": [
    "wooldanji-admin",
    "apartments"
  ],
  "primaryFeature": "wooldanji-admin",
  "features": {
    "wooldanji-admin": {
      "phase": "do",
      "phaseNumber": 3,
      "matchRate": null,
      "iterationCount": 0,
      "requirements": [],
      "documents": {},
      "timestamps": {
        "started": "2026-03-12T06:01:04.548Z",
        "lastUpdated": "2026-03-12T06:01:04.548Z"
      },
      "lastFile": "/Users/hyeonwoo/Code/wooldanji-admin/components/login-form.tsx"
    },
    "apartments": {
      "phase": "do",
      "phaseNumber": 3,
      "matchRate": null,
      "iterationCount": 0,
      "requirements": [],
      "documents": {},
      "timestamps": {
        "started": "2026-03-12T06:02:48.121Z",
        "lastUpdated": "2026-03-12T06:02:52.650Z"
      },
      "lastFile": "/Users/hyeonwoo/Code/wooldanji-admin/app/admin/apartments/page.tsx"
    }
  },
  "pipeline": {
    "currentPhase": 1,
    "level": "Dynamic",
    "phaseHistory": []
  },
  "session": {
    "startedAt": "2026-03-12T06:01:04.548Z",
    "onboardingCompleted": false,
    "lastActivity": "2026-03-12T06:02:52.650Z"
  },
  "history": [
    {
      "timestamp": "2026-03-12T06:01:04.548Z",
      "feature": "wooldanji-admin",
      "phase": "do",
      "action": "updated"
    },
    {
      "timestamp": "2026-03-12T06:02:48.121Z",
      "feature": "apartments",
      "phase": "do",
      "action": "updated"
    },
    {
      "timestamp": "2026-03-12T06:02:52.650Z",
      "feature": "apartments",
      "phase": "do",
      "action": "updated"
    }
  ]
}